pycwatch/lib/__init__.py
pycwatch/lib/client.py
pycwatch/lib/config.py
pycwatch/lib/conversion.py
pycwatch/lib/endpoints.py
pycwatch/lib/exceptions.py
pycwatch/lib/models.py
pycwatch/lib/py.typed
pycwatch/lib/utils.py
pycwatch_lib-2.1.2.dist-info/METADATA
pycwatch_lib-2.1.2.dist-info/WHEEL
pycwatch_lib-2.1.2.dist-info/RECORD
